tkinter_expansion/GuiStyle.py
tkinter_expansion/Identifiers.py
tkinter_expansion/__init__.py
tkinter_expansion-0.1.90.dist-info/LICENSE
tkinter_expansion-0.1.90.dist-info/METADATA
tkinter_expansion-0.1.90.dist-info/WHEEL
tkinter_expansion-0.1.90.dist-info/top_level.txt
tkinter_expansion-0.1.90.dist-info/RECORD
