Metadata-Version: 2.1
Name: tkinter_expansion
Version: 0.1.90
Summary: Python framework that is heavily inspired by JavaFX and makes creating apps easier
Home-page: https://fire-the-fox.github.io/tkinter_expansion_docs/
Author: Fire-The-Fox
Author-email: gajdos.jan77@gmail.com
License: MIT
Download-URL: https://github.com/Fire-The-Fox/tkinter_expansion
Keywords: tkinter,expansion,designer,themes,framework
Platform: UNKNOWN
Classifier: License :: OSI Approved :: MIT License
Classifier: Programming Language :: Python :: 3.7
Classifier: Programming Language :: Python :: 3.8
Classifier: Programming Language :: Python :: 3.9
License-File: LICENSE
